cfdonnx/__init__.py
cfdonnx/__main__.py
cfdonnx/models/__init__.py
cfdonnx/models/torch/AutoEncoder.py
cfdonnx/models/torch/AutoEncoderEx.py
cfdonnx/models/torch/MaxUnpool.py
cfdonnx/models/torch/UNetEx.py
cfdonnx/models/torch/__init__.py
cfdonnx-2.0.1.dist-info/LICENSE.txt
cfdonnx-2.0.1.dist-info/METADATA
cfdonnx-2.0.1.dist-info/WHEEL
cfdonnx-2.0.1.dist-info/top_level.txt
cfdonnx-2.0.1.dist-info/RECORD
