Metadata-Version: 2.1
Name: cfdonnx
Version: 2.0.1
Summary: Converting ML-CFD models to ONNX
Home-page: https://github.com/simzero/cfdonnx
Author: Carlos Pena Monferrer
License: MIT
Keywords: cfd ml onnx
Platform: UNKNOWN
Classifier: Programming Language :: Python :: 3
Classifier: License :: OSI Approved :: MIT License
Classifier: Operating System :: OS Independent
License-File: LICENSE.txt
Requires-Dist: onnx (==1.13.1)
Requires-Dist: onnxruntime (==1.14.1)
Requires-Dist: torch (==2.0.0)
Requires-Dist: torchvision (==0.15.1)
